sbom4python/__init__.py
sbom4python/cli.py
sbom4python/license.py
sbom4python/scanner.py
sbom4python/version.py
sbom4python/license_data/spdx_licenses.json
test/__init__.py
test/test_license.py
sbom4python-0.12.4.dist-info/LICENSE
sbom4python-0.12.4.dist-info/METADATA
sbom4python-0.12.4.dist-info/WHEEL
sbom4python-0.12.4.dist-info/entry_points.txt
sbom4python-0.12.4.dist-info/top_level.txt
sbom4python-0.12.4.dist-info/RECORD
