Metadata-Version: 2.1
Name: sbom4python
Version: 0.12.4
Summary: SBOM generator for Python modules
Home-page: https://github.com/anthonyharrison/sbom4python
Author: Anthony Harrison
Author-email: anthony.p.harrison@gmail.com
Maintainer: Anthony Harrison
Maintainer-email: anthony.p.harrison@gmail.com
License: Apache-2.0
Keywords: security,tools,SBOM,DevSecOps,SPDX,CycloneDX
Classifier: Development Status :: 4 - Beta
Classifier: Intended Audience :: Developers
Classifier: License :: OSI Approved :: Apache Software License
Classifier: Natural Language :: English
Classifier: Operating System :: OS Independent
Classifier: Programming Language :: Python :: 3.7
Classifier: Programming Language :: Python :: 3.8
Classifier: Programming Language :: Python :: 3.9
Classifier: Programming Language :: Python :: 3.10
Classifier: Programming Language :: Python :: 3.11
Classifier: Programming Language :: Python :: 3.12
Classifier: Programming Language :: Python :: 3.13
Classifier: Programming Language :: Python :: Implementation :: CPython
Classifier: Programming Language :: Python :: Implementation :: PyPy
Requires-Python: >=3.7
License-File: LICENSE
Requires-Dist: lib4package (>=0.3.3)
Requires-Dist: lib4sbom (>=0.8.0)
Requires-Dist: sbom2dot (>=0.3.0)
Requires-Dist: sbom4files (>=0.4.4)
Requires-Dist: importlib-metadata (>=3.6) ; python_version < "3.10"
Requires-Dist: toml ; python_version < "3.11"
